README.md
setup.py
common_api_test_engine/__init__.py
common_api_test_engine.egg-info/PKG-INFO
common_api_test_engine.egg-info/SOURCES.txt
common_api_test_engine.egg-info/dependency_links.txt
common_api_test_engine.egg-info/requires.txt
common_api_test_engine.egg-info/top_level.txt
common_api_test_engine/core/DBClient.py
common_api_test_engine/core/__init__.py
common_api_test_engine/core/cases.py
common_api_test_engine/core/runner.py
common_api_test_engine/core/tools.py