Metadata-Version: 2.2
Name: common_api_test_engine
Version: 1.1.4
Author: dawnpopo
Author-email: 1916364638@qq.com
Classifier: Programming Language :: Python :: 3
Requires-Python: >=3.7
Requires-Dist: Faker>=13.4.0
Requires-Dist: jsonpath>=0.82.2
Requires-Dist: pymysql>=1.1.1
Requires-Dist: requests-toolbelt>=0.9.1
Requires-Dist: rsa>=4.8
Dynamic: author
Dynamic: author-email
Dynamic: classifier
Dynamic: description
Dynamic: description-content-type
Dynamic: requires-dist
Dynamic: requires-python
